LICENSE
MANIFEST.in
README.rst
setup.cfg
setup.py
ckip_classic/__init__.py
ckip_classic/ini.py
ckip_classic/parser.py
ckip_classic/ws.py
ckip_classic.egg-info/PKG-INFO
ckip_classic.egg-info/SOURCES.txt
ckip_classic.egg-info/dependency_links.txt
ckip_classic.egg-info/top_level.txt
ckip_classic/client/__init__.py
ckip_classic/client/_parser.py
src/.DS_Store
src/__init__.py
src/parser/__init__.py
src/parser/cckipparser.pxd
src/parser/ckipparser.pyx
src/ws/__init__.py
src/ws/cckipws.pxd
src/ws/ckipws.pyx