Metadata-Version: 2.1
Name: ckip-classic
Version: 1.2.3
Summary: CKIP Classic NLP Tools
Home-page: https://ckip-classic.readthedocs.io
Download-URL: https://ckip-classic.readthedocs.io/tarball/1.2.3
Author: Mu Yang
Author-email: emfomy@gmail.com
License: GPL-3.0
Platform: linux_x86_64
Classifier: Development Status :: 5 - Production/Stable
Classifier: Environment :: Console
Classifier: Programming Language :: Python
Classifier: Programming Language :: Python :: 3
Classifier: Programming Language :: Python :: 3.6
Classifier: Programming Language :: Python :: 3.7
Classifier: Programming Language :: Python :: 3.8
Classifier: Programming Language :: Python :: 3 :: Only
Classifier: Programming Language :: Cython
Classifier: License :: OSI Approved :: GNU General Public License v3 (GPLv3)
Classifier: Operating System :: POSIX :: Linux
Classifier: Natural Language :: Chinese (Traditional)
Requires-Python: >=3.6
License-File: LICENSE
